haystack_integrations/components/connectors/__init__.py
haystack_integrations/components/connectors/weave_connector.py
haystack_integrations/tracing/weave/__init__.py
haystack_integrations/tracing/weave/tracer.py
weights_bias_haystack-0.0.3.dist-info/METADATA
weights_bias_haystack-0.0.3.dist-info/WHEEL
weights_bias_haystack-0.0.3.dist-info/licenses/LICENSE.txt
weights_bias_haystack-0.0.3.dist-info/RECORD
